cowch/__init__.py
cowch-0.4.dist-info/License.txt
cowch-0.4.dist-info/METADATA
cowch-0.4.dist-info/WHEEL
cowch-0.4.dist-info/top_level.txt
cowch-0.4.dist-info/RECORD
