Metadata-Version: 2.1
Name: cowch
Version: 0.4
Summary: This package dosen't make any sense to download
Home-page: UNKNOWN
Author: ANSHUMAN
Author-email: abc@gmail.com
License: UNKNOWN
Platform: UNKNOWN
Classifier: Programming Language :: Python :: 3
Classifier: License :: OSI Approved :: MIT License
Classifier: Operating System :: OS Independent
